cakephpsphinx/__init__.py
cakephpsphinx/config/__init__.py
cakephpsphinx/config/all.py
cakephpsphinx/config/cakei18n.py
cakephpsphinx/config/release_context.py
cakephpsphinx/themes/cakephp/globaltoc.html
cakephpsphinx/themes/cakephp/layout.html
cakephpsphinx/themes/cakephp/localtoc.html
cakephpsphinx/themes/cakephp/search.html
cakephpsphinx/themes/cakephp/theme.conf
cakephpsphinx/themes/cakephp/menu/business-solutions.html
cakephpsphinx/themes/cakephp/menu/community.html
cakephpsphinx/themes/cakephp/menu/documentation.html
cakephpsphinx/themes/cakephp/menu/footer-documentation.html
cakephpsphinx/themes/cakephp/menu/help.html
cakephpsphinx/themes/cakephp/static/favicon.png
cakephpsphinx/themes/cakephp/static/linode.png
cakephpsphinx/themes/cakephp/static/logo-cake.png
cakephpsphinx/themes/cakephp/static/open-hub.svg
cakephpsphinx/themes/cakephp/static/pdf-logo.png
cakephpsphinx/themes/cakephp/static/pingping.png
cakephpsphinx/themes/cakephp/static/search.png
cakephpsphinx/themes/cakephp/static/css/bootstrap.min.css
cakephpsphinx/themes/cakephp/static/css/default.css
cakephpsphinx/themes/cakephp/static/css/font-awesome.min.css
cakephpsphinx/themes/cakephp/static/css/fonts.css
cakephpsphinx/themes/cakephp/static/css/pygments.css
cakephpsphinx/themes/cakephp/static/css/responsive.css
cakephpsphinx/themes/cakephp/static/css/style.css
cakephpsphinx/themes/cakephp/static/favicons/android-chrome-192x192.png
cakephpsphinx/themes/cakephp/static/favicons/android-chrome-512x512.png
cakephpsphinx/themes/cakephp/static/favicons/apple-touch-icon.png
cakephpsphinx/themes/cakephp/static/favicons/browserconfig.xml
cakephpsphinx/themes/cakephp/static/favicons/favicon-16x16.png
cakephpsphinx/themes/cakephp/static/favicons/favicon-32x32.png
cakephpsphinx/themes/cakephp/static/favicons/favicon.ico
cakephpsphinx/themes/cakephp/static/favicons/favicon.png
cakephpsphinx/themes/cakephp/static/favicons/favicon.svg
cakephpsphinx/themes/cakephp/static/favicons/manifest.json
cakephpsphinx-0.1.66.dist-info/LICENSE
cakephpsphinx-0.1.66.dist-info/METADATA
cakephpsphinx-0.1.66.dist-info/WHEEL
cakephpsphinx-0.1.66.dist-info/entry_points.txt
cakephpsphinx-0.1.66.dist-info/top_level.txt
cakephpsphinx-0.1.66.dist-info/RECORD
