Metadata-Version: 2.1
Name: cakephpsphinx
Version: 0.1.66
Summary: CakePHP Sphinx theme and common configuration
Home-page: https://book.cakephp.org
Author: CakePHP Community
Author-email: docs@cakephp.org
License: UNKNOWN
Platform: UNKNOWN
License-File: LICENSE
